saleor/__init__.py
saleor/account/__init__.py
saleor/account/emails.py
saleor/account/error_codes.py
saleor/account/events.py
saleor/account/forms.py
saleor/account/i18n.py
saleor/account/management/__init__.py
saleor/account/management/commands/__init__.py
saleor/account/management/commands/changepassword.py
saleor/account/management/commands/createsuperuser.py
saleor/account/migrations/0001_initial.py
saleor/account/migrations/0002_auto_20150907_0602.py
saleor/account/migrations/0003_auto_20151104_1102.py
saleor/account/migrations/0004_auto_20160114_0419.py
saleor/account/migrations/0005_auto_20160205_0651.py
saleor/account/migrations/0006_auto_20160829_0819.py
saleor/account/migrations/0007_auto_20161115_0940.py
saleor/account/migrations/0008_auto_20161115_1011.py
saleor/account/migrations/0009_auto_20170206_0407.py
saleor/account/migrations/0010_auto_20170919_0839.py
saleor/account/migrations/0011_auto_20171110_0552.py
saleor/account/migrations/0012_auto_20171117_0846.py
saleor/account/migrations/0013_auto_20171120_0521.py
saleor/account/migrations/0014_auto_20171129_1004.py
saleor/account/migrations/0015_auto_20171213_0734.py
saleor/account/migrations/0016_auto_20180108_0814.py
saleor/account/migrations/0017_auto_20180206_0957.py
saleor/account/migrations/0018_auto_20180426_0641.py
saleor/account/migrations/0019_auto_20180528_1205.py
saleor/account/migrations/0020_user_token.py
saleor/account/migrations/0021_unique_token.py
saleor/account/migrations/0022_auto_20180718_0956.py
saleor/account/migrations/0023_auto_20180719_0520.py
saleor/account/migrations/0024_auto_20181011_0737.py
saleor/account/migrations/0025_auto_20190314_0550.py
saleor/account/migrations/0026_user_avatar.py
saleor/account/migrations/0027_customerevent.py
saleor/account/migrations/0028_user_private_meta.py
saleor/account/migrations/0029_user_meta.py
saleor/account/migrations/0030_auto_20190719_0733.py
saleor/account/migrations/0031_auto_20190719_0745.py
saleor-2.10.1.dist-info/LICENSE
saleor-2.10.1.dist-info/WHEEL
saleor-2.10.1.dist-info/METADATA
saleor-2.10.1.dist-info/RECORD
