Metadata-Version: 2.1
Name: saleor
Version: 2.10.1
Summary: A modular, high performance e-commerce storefront built with GraphQL, Django, and ReactJS.
Home-page: https://getsaleor.com/
License: BSD-3-Clause
Author: Mirumee Software
Author-email: hello@mirumee.com
Requires-Python: >=3.8,<3.9
Classifier: License :: OSI Approved :: BSD License
Classifier: Programming Language :: Python :: 3
Classifier: Programming Language :: Python :: 3.8
Requires-Dist: babel (>=2.8,<2.9)
Requires-Dist: boto3 (>=1.12,<2.0)
Requires-Dist: braintree (>=3.49.0,<3.50.0)
Requires-Dist: celery[redis] (>=4.3.0,<5.0.0)
Requires-Dist: dj-database-url (>=0,<1)
Requires-Dist: dj-email-url (>=1,<2)
Requires-Dist: django (>=3.0.6,<4.0.0)
Requires-Dist: django-cache-url (>=3.1.2,<4.0.0)
Requires-Dist: django-countries (>=6.1,<7.0)
Requires-Dist: django-filter (>=2.2,<3.0)
Requires-Dist: django-graphql-jwt (==0.3.0)
Requires-Dist: django-measurement (>=3.0,<4.0)
Requires-Dist: django-mptt (>=0,<1)
Requires-Dist: django-phonenumber-field (>=4.0,<5.0)
Requires-Dist: django-prices (>=2.1,<3.0)
Requires-Dist: django-prices-openexchangerates (>=1.0.1,<2.0.0)
Requires-Dist: django-prices-vatlayer (>=1.1.0,<2.0.0)
Requires-Dist: django-storages[google] (>=1.7.1,<2.0.0)
Requires-Dist: django-templated-email (>=2.3.0,<3.0.0)
Requires-Dist: django-versatileimagefield (>=2.0,<3.0)
Requires-Dist: draftjs-sanitizer (>=1.0.0,<2.0.0)
Requires-Dist: faker (>=4.0,<5.0)
Requires-Dist: freezegun (>=0,<1)
Requires-Dist: google-cloud-storage (>=1.18.0,<2.0.0)
Requires-Dist: google-i18n-address (>=2.3.5,<3.0.0)
Requires-Dist: google-measurement-protocol (>=1.0,<2.0)
Requires-Dist: graphene-django (>=2.9.1,<3.0.0)
Requires-Dist: graphene-federation (>=0.1.0,<0.2.0)
Requires-Dist: html-to-draftjs (>=1.0.1,<2.0.0)
Requires-Dist: jaeger-client (>=4.3.0,<5.0.0)
Requires-Dist: markdown (>=3.1.1,<4.0.0)
Requires-Dist: maxminddb (>=1.5.4,<2.0.0)
Requires-Dist: maxminddb-geolite2 (>=2018.701,<2019.0)
Requires-Dist: oauthlib (>=3.0,<4.0)
Requires-Dist: opentracing (>=2.3.0,<3.0.0)
Requires-Dist: phonenumberslite (>=8.12.2,<9.0.0)
Requires-Dist: prices (>=1.0,<2.0)
Requires-Dist: psycopg2-binary (>=2.8.3,<3.0.0)
Requires-Dist: purl (>=1.5,<2.0)
Requires-Dist: python-magic-bin (>=0.4.14,<0.5.0); sys_platform == "win32"
Requires-Dist: razorpay (>=1.2,<2.0)
Requires-Dist: requests (>=2.22,<3.0)
Requires-Dist: sentry-sdk (>=0,<1)
Requires-Dist: stripe (>=2.47.0,<3.0.0)
Requires-Dist: text-unidecode (>=1.2,<2.0)
Requires-Dist: tqdm (>=4.36,<5.0)
Requires-Dist: uwsgi (>=2.0.8,<3.0.0); sys_platform != "win32"
Requires-Dist: weasyprint (>=48)
Project-URL: Documentation, https://docs.getsaleor.com/en/latest/
Project-URL: Repository, https://github.com/mirumee/saleor
